processrepo/Process.py
processrepo/ProcessRunProfile.py
processrepo/__init__.py
processrepo/repository/ProcessRepository.py
processrepo/repository/ProcessRunProfileRepository.py
processrepo/repository/__init__.py
processrepo/repository/serialize/__init__.py
processrepo/repository/serialize/process_deserializer.py
processrepo/repository/serialize/process_run_profile_deserializer.py
processrepo/repository/serialize/process_run_profile_serializer.py
processrepo/repository/serialize/process_serializer.py
persuader_technology_automata_process_repository-0.2.1.dist-info/LICENSE
persuader_technology_automata_process_repository-0.2.1.dist-info/METADATA
persuader_technology_automata_process_repository-0.2.1.dist-info/WHEEL
persuader_technology_automata_process_repository-0.2.1.dist-info/top_level.txt
persuader_technology_automata_process_repository-0.2.1.dist-info/RECORD
