Metadata-Version: 2.1
Name: persuader-technology-automata-process-repository
Version: 0.2.1
Summary: Automata Process Repository
Author: Persuader Technology
Author-email: software@persuader.technology
License: UNLICENSE
Classifier: Programming Language :: Python :: 3
License-File: LICENSE
Requires-Dist: persuader-technology-automata-core (>=0.6.0)
Requires-Dist: persuader-technology-automata-logger (>=0.0.5)
Requires-Dist: persuader-technology-automata-redis (>=0.3.8)
